enckey/__init__.py
enckey/enckey.py
enckey/key.py
enckey-0.0.2.dist-info/LICENSE.txt
enckey-0.0.2.dist-info/METADATA
enckey-0.0.2.dist-info/WHEEL
enckey-0.0.2.dist-info/top_level.txt
enckey-0.0.2.dist-info/RECORD
